README.md
setup.py
conflictify/__init__.py
conflictify.egg-info/PKG-INFO
conflictify.egg-info/SOURCES.txt
conflictify.egg-info/dependency_links.txt
conflictify.egg-info/requires.txt
conflictify.egg-info/top_level.txt